armonik_cli/__init__.py
armonik_cli/_version.py
armonik_cli/cli.py
armonik_cli/exceptions.py
armonik_cli/utils.py
armonik_cli/commands/__init__.py
armonik_cli/commands/cluster.py
armonik_cli/commands/config.py
armonik_cli/commands/partitions.py
armonik_cli/commands/results.py
armonik_cli/commands/sessions.py
armonik_cli/commands/tasks.py
armonik_cli/core/__init__.py
armonik_cli/core/common.py
armonik_cli/core/configuration.py
armonik_cli/core/console.py
armonik_cli/core/decorators.py
armonik_cli/core/filter_grammar.lark
armonik_cli/core/filters.py
armonik_cli/core/logging.py
armonik_cli/core/options.py
armonik_cli/core/params.py
armonik_cli/core/serialize.py
masivclipubtest-0.3.0.dist-info/LICENSE
masivclipubtest-0.3.0.dist-info/METADATA
masivclipubtest-0.3.0.dist-info/WHEEL
masivclipubtest-0.3.0.dist-info/entry_points.txt
masivclipubtest-0.3.0.dist-info/top_level.txt
masivclipubtest-0.3.0.dist-info/RECORD
