Metadata-Version: 2.2
Name: masivclipubtest
Version: 0.3.0
Summary: Command-line tool to monitor and manage ArmoniK clusters.
License: Apache v2.0 LICENSE
Project-URL: Homepage, https://github.com/AncientPatata/ArmoniK.CLI-pipelines
Project-URL: Bug Tracker, https://github.com/AncientPatata/ArmoniK.CLI-pipelines/issues
Keywords: cloud,HTC,CLI
Classifier: Development Status :: 4 - Beta
Classifier: Intended Audience :: Developers
Classifier: License :: OSI Approved :: Apache Software License
Classifier: Programming Language :: Python
Classifier: Programming Language :: Python :: 3.8
Classifier: Programming Language :: Python :: 3.9
Classifier: Programming Language :: Python :: 3.10
Classifier: Programming Language :: Python :: 3.11
Classifier: Operating System :: OS Independent
Classifier: Topic :: Internet
Requires-Python: >=3.8
License-File: LICENSE
Requires-Dist: armonik>=3.25.0
Requires-Dist: click
Requires-Dist: lark
Requires-Dist: PyYAML
Requires-Dist: rich_click
Requires-Dist: typing_extensions
Requires-Dist: pydantic
Requires-Dist: pydantic-yaml
Provides-Extra: tests
Requires-Dist: coverage; extra == "tests"
Requires-Dist: pytest; extra == "tests"
Requires-Dist: pytest-cov; extra == "tests"
Requires-Dist: pytest-mock; extra == "tests"
Requires-Dist: pytest-benchmark[histogram]; extra == "tests"
Provides-Extra: dev
Requires-Dist: mypy; extra == "dev"
Requires-Dist: ruff; extra == "dev"
Requires-Dist: types-PyYAML; extra == "dev"
Provides-Extra: docs
Requires-Dist: sphinx; extra == "docs"
Requires-Dist: sphinx-click; extra == "docs"
Requires-Dist: sphinx-rtd-theme; extra == "docs"
Requires-Dist: sphinx-autobuild; extra == "docs"
